work_assistant_mcp/__init__.py
work_assistant_mcp/mcp_debug.log
work_assistant_mcp/server.py
work_assistant_mcp-0.3.0.dist-info/METADATA
work_assistant_mcp-0.3.0.dist-info/WHEEL
work_assistant_mcp-0.3.0.dist-info/entry_points.txt
work_assistant_mcp-0.3.0.dist-info/RECORD
