Metadata-Version: 2.4
Name: work-assistant-mcp
Version: 0.3.0
Summary: Work Assistant MCP Server - 프로세스 생성, 조회, 실행, 회사 정보 질의 도구
Project-URL: Homepage, https://github.com/uengine-oss/work-assistant-mcp
Author-email: uEngine <help@uengine.org>
License: MIT
Keywords: bpm,fastmcp,mcp,process,work-assistant
Classifier: Development Status :: 3 - Alpha
Classifier: Intended Audience :: Developers
Classifier: License :: OSI Approved :: MIT License
Classifier: Programming Language :: Python :: 3
Classifier: Programming Language :: Python :: 3.10
Classifier: Programming Language :: Python :: 3.11
Classifier: Programming Language :: Python :: 3.12
Requires-Python: >=3.10
Requires-Dist: fastmcp>=0.1.0
Requires-Dist: httpx>=0.27.0
